README.rst
jabbergram.py
setup.py
jabbergram.egg-info/PKG-INFO
jabbergram.egg-info/SOURCES.txt
jabbergram.egg-info/dependency_links.txt
jabbergram.egg-info/requires.txt
jabbergram.egg-info/top_level.txt