Metadata-Version: 1.1
Name: jabbergram
Version: 0.1.6
Summary: XMPP/Jabber - Telegram Gateway.
Home-page: http://daemons.cf/cgit/jabbergram/about/
Author: drymer
Author-email: drymer@autistici.org
License: GPLv3
Download-URL: http://daemons.cf/cgit/jabbergram/snapshot/jabbergram-0.1.6.tar.gz
Platform: UNKNOWN
Classifier: Development Status :: 4 - Beta
Classifier: Programming Language :: Python
Classifier: Programming Language :: Python :: 3
Classifier: Programming Language :: Python :: 3.4
Classifier: Programming Language :: Python :: 3.5
Classifier: Operating System :: OS Independent
Classifier: Operating System :: POSIX
Classifier: Intended Audience :: End Users/Desktop
